alek/__init__.py
alek/_alek.py
alek-0.1.5.dist-info/METADATA
alek-0.1.5.dist-info/WHEEL
alek-0.1.5.dist-info/top_level.txt
alek-0.1.5.dist-info/RECORD
