Metadata-Version: 2.1
Name: alek
Version: 0.1.5
Summary: Alek Chase's personal python library
Home-page: https://github.com/AlekTheCoder/alek
Author: Alek Chase
Author-email: no-reply@gmail.com
License: MIT
Keywords: alek
Platform: UNKNOWN
Requires-Python: >=3.5
